seclab_taskflows/__about__.py
seclab_taskflows/__init__.py
seclab_taskflows/configs/model_config.yaml
seclab_taskflows/configs/model_config_codeql_python.yaml
seclab_taskflows/configs/model_config_lowercost.yaml
seclab_taskflows/mcp_servers/alert_results_models.py
seclab_taskflows/mcp_servers/gh_actions.py
seclab_taskflows/mcp_servers/gh_code_scanning.py
seclab_taskflows/mcp_servers/gh_file_viewer.py
seclab_taskflows/mcp_servers/ghsa.py
seclab_taskflows/mcp_servers/local_file_viewer.py
seclab_taskflows/mcp_servers/local_gh_resources.py
seclab_taskflows/mcp_servers/repo_context.py
seclab_taskflows/mcp_servers/repo_context_models.py
seclab_taskflows/mcp_servers/report_alert_state.py
seclab_taskflows/mcp_servers/utils.py
seclab_taskflows/mcp_servers/codeql_python/README.md
seclab_taskflows/mcp_servers/codeql_python/codeql_sqlite_models.py
seclab_taskflows/mcp_servers/codeql_python/mcp_server.py
seclab_taskflows/mcp_servers/codeql_python/queries/mcp-python/codeql-pack.lock.yml
seclab_taskflows/mcp_servers/codeql_python/queries/mcp-python/codeql-pack.yml
seclab_taskflows/mcp_servers/codeql_python/queries/mcp-python/example.ql
seclab_taskflows/mcp_servers/codeql_python/queries/mcp-python/remote_sources.ql
seclab_taskflows/personalities/action_expert.yaml
seclab_taskflows/personalities/auditor.yaml
seclab_taskflows/personalities/web_application_security_expert.yaml
seclab_taskflows/prompts/audit/audit_issue.yaml
seclab_taskflows/prompts/triage_taskflows/actions_common/check_dismiss_reason.yaml
seclab_taskflows/prompts/triage_taskflows/actions_common/dismiss_decision.yaml
seclab_taskflows/taskflows/alert_triage_examples/README.md
seclab_taskflows/taskflows/alert_triage_examples/triage_common/check_notes.yaml
seclab_taskflows/taskflows/alert_triage_examples/triage_common/fetch_code_scanning_alerts.yaml
seclab_taskflows/taskflows/alert_triage_examples/triage_common/reachability_analysis.yaml
seclab_taskflows-0.0.3.dist-info/METADATA
seclab_taskflows-0.0.3.dist-info/WHEEL
seclab_taskflows-0.0.3.dist-info/licenses/LICENSE
seclab_taskflows-0.0.3.dist-info/RECORD
