Metadata-Version: 2.4
Name: seclab-taskflows
Version: 0.0.3
Summary: Example taskflows to use with the the GitHub Security Lab Taskflow Agent Framework (https://github.com/GitHubSecurityLab/seclab-taskflow-agent)
Project-URL: Source, https://github.com/GitHubSecurityLab/seclab-taskflows
Project-URL: Issues, https://github.com/GitHubSecurityLab/seclab-taskflows/issues
Author-email: GitHub Security Lab <securitylab@github.com>
License-Expression: MIT
License-File: LICENSE
Classifier: Development Status :: 4 - Beta
Classifier: Programming Language :: Python
Classifier: Programming Language :: Python :: 3.8
Classifier: Programming Language :: Python :: 3.9
Classifier: Programming Language :: Python :: 3.10
Classifier: Programming Language :: Python :: 3.11
Classifier: Programming Language :: Python :: 3.12
Classifier: Programming Language :: Python :: Implementation :: CPython
Classifier: Programming Language :: Python :: Implementation :: PyPy
Requires-Python: >=3.9
Requires-Dist: seclab-taskflow-agent
